README.md
setup.cfg
setup.py
nionswift_elabftw_plugin.egg-info/PKG-INFO
nionswift_elabftw_plugin.egg-info/SOURCES.txt
nionswift_elabftw_plugin.egg-info/dependency_links.txt
nionswift_elabftw_plugin.egg-info/requires.txt
nionswift_elabftw_plugin.egg-info/top_level.txt
nionswift_plugin/nionswift_elabftw_plugin/AsyncRequestWrapper.py
nionswift_plugin/nionswift_elabftw_plugin/ConflictCheckDialog.py
nionswift_plugin/nionswift_elabftw_plugin/MergeDataConfirmDialog.py
nionswift_plugin/nionswift_elabftw_plugin/Users.py
nionswift_plugin/nionswift_elabftw_plugin/__init__.py
nionswift_plugin/nionswift_elabftw_plugin/elabftw.py