Metadata-Version: 1.1
Name: nionswift-elabftw-plugin
Version: 0.1.2.4
Summary: A simple plugin to allow users to manage their ElabFTW experiments metadata through Nionswift.
Home-page: https://github.com/shabihsherjeel/nionswift_elabftw_plugin
Author: Sherjeel Shabih
Author-email: shabihsherjeel@gmail.com
License: GNU General Public License v3.0
Download-URL: https://github.com/shabihsherjeel/nionswift_elabftw_plugin/archive/v0.1.2.4-alpha.tar.gz
Keywords: NIONSWIFT,ELABFTW,ELN,PLUGIN
Platform: UNKNOWN
Classifier: Development Status :: 3 - Alpha
Classifier: Intended Audience :: Science/Research
Classifier: Programming Language :: Python :: 3
